prueba/prueba_tb.v
module prueba();

  wire w1,w2,out;
  reg  A,B,C;

  not U1(w1, A);
  and U2(w2, w1, B);
  or  U3(out, w1, w2, C);

  initial begin
    $display("A B C | Y");
    $display("------|--");
    $monitor("%b %b %b | %b", A, B, C, out);
    A = 0; B = 0; C = 0;
    #1 C = 1;
    #1 B = 1; C = 0;
    #1 B = 1; C = 1;
    #1 A = 1; B = 0; C = 0;
    #1 A = 1; B = 0; C = 1;
    #1 A = 1; B = 1; C = 0;
    #1 A = 1; B = 1; C = 1;
    #1 $finish;
  end

  initial begin
    $dumpfile("prueba_tb.vcd");
    $dumpvars(0, prueba);
  end
endmodule

prueba/prueba_tb.vcd
$date
	Fri Jul 31 17:13:09 2020
$end
$version
	Icarus Verilog
$end
$timescale
	1ps
$end
$scope module prueba $end
$var wire 1 ! out $end
$var wire 1 " w1 $end
$var wire 1 # w2 $end
$var reg 1 $ A $end
$var reg 1 % B $end
$var reg 1 & C $end
$upscope $end
$enddefinitions $end
#0
$dumpvars
0&
0%
0$
0#
1"
1!
$end
#1
1&
#2
1#
0&
1%
#3
1&
#4
0!
0#
0"
0&
0%
1$
#5
1!
1&
#6
0!
0&
1%
#7
1!
1&
